dot/__init__.py
dot/dot.py
print_dot_salamtam-0.0.3.dist-info/METADATA
print_dot_salamtam-0.0.3.dist-info/WHEEL
print_dot_salamtam-0.0.3.dist-info/top_level.txt
print_dot_salamtam-0.0.3.dist-info/RECORD
