Metadata-Version: 2.1
Name: print-dot-salamtam
Version: 0.0.3
Summary: print dot for test the coding work
Home-page: https://github.com/salamtamp/print-dot
Author: salamtam
Author-email: salamtam.p@gmail.com
License: UNKNOWN
Platform: UNKNOWN
Classifier: Programming Language :: Python :: 3
Classifier: License :: OSI Approved :: MIT License
Classifier: Operating System :: OS Independent
Requires-Python: >=3.6
